LICENSE
MANIFEST.in
README.rst
changelog.md
setup.py
examples/README.md
lib/__init__.py
lib/models.py
lib/riskManagement.py
lib/clients/__init__.py
lib/clients/domain_client.py
lib/clients/domain_client_test.py
lib/clients/errorHandler.py
lib/clients/httpClient.py
lib/clients/httpClient_test.py
lib/clients/timeoutException.py
lib/clients/equityTracking/__init__.py
lib/clients/equityTracking/drawdownListener.py
lib/clients/equityTracking/drawdownListenerManager.py
lib/clients/equityTracking/drawdownListenerManager_test.py
lib/clients/equityTracking/equityTracking_client.py
lib/clients/equityTracking/equityTracking_client_test.py
metaapi_cloud_risk_management_sdk.egg-info/PKG-INFO
metaapi_cloud_risk_management_sdk.egg-info/SOURCES.txt
metaapi_cloud_risk_management_sdk.egg-info/dependency_links.txt
metaapi_cloud_risk_management_sdk.egg-info/requires.txt
metaapi_cloud_risk_management_sdk.egg-info/top_level.txt