Metadata-Version: 2.1
Name: metaapi-cloud-risk-management-sdk
Version: 2.0.2
Summary: Python SDK for MetaApi risk management API. Can execute trading risk restrictions, forex challenges and competitions in a cloud on both MetaTrader 5 (MT5) and MetaTrader 4 (MT4) (https://metaapi.cloud)
Home-page: https://github.com/metaapi/metaapi-risk-management-python-sdk
Author: MetaApi DMCC
Author-email: support@metaapi.cloud
License: SEE LICENSE IN LICENSE
Keywords: metaapi.cloud,MetaTrader,MetaTrader 5,MetaTrader 4,MetaTrader5,MetaTrader4,MT,MT4,MT5,forex,equity tracking,risk management,API,REST,client,sdk,cloud,ftmo,prop trading,proprietary trading
Classifier: Programming Language :: Python :: 3
Classifier: License :: Other/Proprietary License
Classifier: Operating System :: OS Independent
Requires-Python: >=3.6
License-File: LICENSE
